timeswipe.so
timeswipe.so.1
test_timeswipe_aarch64-0.0.15.dist-info/LICENSE
test_timeswipe_aarch64-0.0.15.dist-info/METADATA
test_timeswipe_aarch64-0.0.15.dist-info/WHEEL
test_timeswipe_aarch64-0.0.15.dist-info/top_level.txt
test_timeswipe_aarch64-0.0.15.dist-info/RECORD
