Metadata-Version: 2.1
Name: test-timeswipe-aarch64
Version: 0.0.15
Summary: TimeSwipe python3 module
Home-page: https://github.com/panda-official/TimeSwipe
Author: Ilya Gavrilov
Author-email: gilyav@gmail.com
License: UNKNOWN
Platform: UNKNOWN
Classifier: Programming Language :: Python :: 3
Classifier: License :: OSI Approved :: MIT License
Classifier: Operating System :: OS Independent
Requires-Dist: cmake-setuptools
